{
  "type": "forge:conditional",
  "recipes": [
    {
      "conditions": [
        {
          "type": "forge:mod_loaded",
          "modid": "quark"
        }
      ],
      "recipe": {
        "type": "minecraft:crafting_shaped",
        "category": "misc",
        "key": {
          "#": {
            "item": "biomesoplenty:dead_wood"
          }
        },
        "pattern": [
          "#",
          "#",
          "#"
        ],
        "result": {
          "count": 8,
          "item": "compatoplenty:dead_post"
        },
        "show_notification": true
      }
    }
  ]
}